setup.py
nephoria/__init__.py
nephoria/exceptions.py
nephoria/testcontroller.py
nephoria/usercontext.py
nephoria.egg-info/PKG-INFO
nephoria.egg-info/SOURCES.txt
nephoria.egg-info/dependency_links.txt
nephoria.egg-info/pbr.json
nephoria.egg-info/requires.txt
nephoria.egg-info/top_level.txt
nephoria/aws/__init__.py
nephoria/aws/autoscaling/__init__.py
nephoria/aws/autoscaling/asops.py
nephoria/aws/cloudformation/__init__.py
nephoria/aws/cloudformation/cfnops.py
nephoria/aws/cloudwatch/__init__.py
nephoria/aws/cloudwatch/cwops.py
nephoria/aws/ec2/__init__.py
nephoria/aws/ec2/b3_ec2ops.py
nephoria/aws/ec2/conversiontask.py
nephoria/aws/ec2/ec2ops.py
nephoria/aws/ec2/euinstance.py
nephoria/aws/ec2/eusnapshot.py
nephoria/aws/ec2/euvolume.py
nephoria/aws/ec2/euzone.py
nephoria/aws/ec2/windows_instance.py
nephoria/aws/elb/__init__.py
nephoria/aws/elb/elbops.py
nephoria/aws/iam/__init__.py
nephoria/aws/iam/iamops.py
nephoria/aws/s3/__init__.py
nephoria/aws/s3/s3ops.py
nephoria/aws/sts/__init__.py
nephoria/aws/sts/stsops.py
nephoria/baseops/__init__.py
nephoria/baseops/boto3baseops.py
nephoria/baseops/botobaseops.py
nephoria/euca/__init__.py
nephoria/euca/taggedresource.py
nephoria/testcase_utils/__init__.py
nephoria/testcase_utils/argparse_to_dict.py
nephoria/testcase_utils/cli_test_runner.py
nephoria/testcase_utils/euconfig.py
nephoria/testcase_utils/process_manager.py
nephoria/testcases/__init__.py
nephoria/testcases/sample_test_suite.py
nephoria/testcases/admintests/__init__.py
nephoria/testcases/admintests/instance_migration.py
nephoria/testcases/admintests/sos_reports.py
nephoria/testcases/ec2/__init__.py
nephoria/testcases/ec2/base_ec2_template.py
nephoria/testcases/ec2/ebs/__init__.py
nephoria/testcases/ec2/ebs/ebs_integrity_check.py
nephoria/testcases/ec2/ebs/legacy_ebs_test_suite.py
nephoria/testcases/ec2/images/__init__.py
nephoria/testcases/ec2/images/load_bfebs_image.py
nephoria/testcases/ec2/images/load_hvm_image.py
nephoria/testcases/ec2/images/load_pv_image.py
nephoria/testcases/ec2/instances/__init__.py
nephoria/testcases/ec2/instances/instance_batch_test.py
nephoria/testcases/ec2/instances/legacy_instance_test_suite.py
