Metadata-Version: 1.1
Name: nephoria
Version: 2.2
Summary: Test Framework and utilities for AWS compatible clouds
Home-page: https://github.com/eucalyptus/nephoria
Author: UNKNOWN
Author-email: UNKNOWN
License: BSD (Simplified)
Platform: Posix; MacOS X; Windows
Classifier: Development Status :: 3 - Alpha
Classifier: Intended Audience :: System Administrators
Classifier: License :: OSI Approved :: BSD License
Classifier: Operating System :: OS Independent
Classifier: Topic :: System :: Systems Administration
